Metadata-Version: 1.0
Name: elvis
Version: 0.1.2
Summary: Framework to homogenize and combine the output of different entity linking tools.
Home-page: UNKNOWN
Author: Sergio Oramas
Author-email: sergio DOT oramas AT upf DOT edu
License: MIT
Platform: UNKNOWN
